Metadata-Version: 2.0
Name: tensorci
Version: 1.0.0
Summary: TensorCI CLI
Home-page: UNKNOWN
Author: Ben Whittle
Author-email: benwhittle31@gmail.com
License: MIT
Platform: UNKNOWN
Requires-Dist: click
Requires-Dist: awesome-slugify
Requires-Dist: requests
Requires-Dist: requests-toolbelt
Requires-Dist: tinynetrc
Requires-Dist: pyyaml
Requires-Dist: gitpython
Requires-Dist: clint
